spreadsheet_to_dictionary/__init__.py
spreadsheet_to_dictionary/generate.py
spreadsheet_to_dictionary-0.0.1.dist-info/LICENSE
spreadsheet_to_dictionary-0.0.1.dist-info/METADATA
spreadsheet_to_dictionary-0.0.1.dist-info/WHEEL
spreadsheet_to_dictionary-0.0.1.dist-info/top_level.txt
spreadsheet_to_dictionary-0.0.1.dist-info/RECORD
