Metadata-Version: 2.1
Name: spreadsheet-to-dictionary
Version: 0.0.1
Summary: A library to convert spreadsheets into a Python dictionary
Home-page: https://github.com/h4n53l/excel_to_dictionary
Author: Jonathan Hansel Awo
Author-email: hanselsoftwaredev@gmail.com
Project-URL: Bug Tracker, https://github.com/h4n53l/excel_to_dictionary/issues
Classifier: Programming Language :: Python :: 3
Classifier: License :: OSI Approved :: MIT License
Classifier: Operating System :: OS Independent
Requires-Python: >=3.6
License-File: LICENSE
Requires-Dist: openpyxl
